{
  "schemaVersion": 1,
  "tags": {
    "arc:syrup-village": {
      "label": "Syrup Village",
      "color": "#59636f",
      "textColor": "#ffffff",
      "description": "Syrup Village tag for One Piece Syrup Village retrieval and filtering.",
      "aliases": [],
      "parents": [],
      "sensitive": false,
      "deprecated": false,
      "replacement": ""
    },
    "character:buchi": {
      "label": "Buchi",
      "color": "#59636f",
      "textColor": "#ffffff",
      "description": "Buchi tag for One Piece Syrup Village retrieval and filtering.",
      "aliases": [],
      "parents": [],
      "sensitive": false,
      "deprecated": false,
      "replacement": ""
    },
    "character:jango": {
      "label": "Jango",
      "color": "#59636f",
      "textColor": "#ffffff",
      "description": "Jango tag for One Piece Syrup Village retrieval and filtering.",
      "aliases": [],
      "parents": [],
      "sensitive": false,
      "deprecated": false,
      "replacement": ""
    },
    "character:kaya": {
      "label": "Kaya",
      "color": "#59636f",
      "textColor": "#ffffff",
      "description": "Kaya tag for One Piece Syrup Village retrieval and filtering.",
      "aliases": [],
      "parents": [],
      "sensitive": false,
      "deprecated": false,
      "replacement": ""
    },
    "character:klahadore": {
      "label": "Klahadore",
      "color": "#59636f",
      "textColor": "#ffffff",
      "description": "Klahadore tag for One Piece Syrup Village retrieval and filtering.",
      "aliases": [],
      "parents": [],
      "sensitive": false,
      "deprecated": false,
      "replacement": ""
    },
    "character:kuro": {
      "label": "Kuro",
      "color": "#59636f",
      "textColor": "#ffffff",
      "description": "Kuro tag for One Piece Syrup Village retrieval and filtering.",
      "aliases": [],
      "parents": [],
      "sensitive": false,
      "deprecated": false,
      "replacement": ""
    },
    "character:merry": {
      "label": "Merry",
      "color": "#59636f",
      "textColor": "#ffffff",
      "description": "Merry tag for One Piece Syrup Village retrieval and filtering.",
      "aliases": [],
      "parents": [],
      "sensitive": false,
      "deprecated": false,
      "replacement": ""
    },
    "character:monkey-d-luffy": {
      "label": "Monkey D. Luffy",
      "color": "#59636f",
      "textColor": "#ffffff",
      "description": "Monkey D. Luffy tag for One Piece Syrup Village retrieval and filtering.",
      "aliases": [],
      "parents": [],
      "sensitive": false,
      "deprecated": false,
      "replacement": ""
    },
    "character:nami": {
      "label": "Nami",
      "color": "#59636f",
      "textColor": "#ffffff",
      "description": "Nami tag for One Piece Syrup Village retrieval and filtering.",
      "aliases": [],
      "parents": [],
      "sensitive": false,
      "deprecated": false,
      "replacement": ""
    },
    "character:ninjin": {
      "label": "Ninjin",
      "color": "#59636f",
      "textColor": "#ffffff",
      "description": "Ninjin tag for One Piece Syrup Village retrieval and filtering.",
      "aliases": [],
      "parents": [],
      "sensitive": false,
      "deprecated": false,
      "replacement": ""
    },
    "character:piiman": {
      "label": "Piiman",
      "color": "#59636f",
      "textColor": "#ffffff",
      "description": "Piiman tag for One Piece Syrup Village retrieval and filtering.",
      "aliases": [],
      "parents": [],
      "sensitive": false,
      "deprecated": false,
      "replacement": ""
    },
    "character:roronoa-zoro": {
      "label": "Roronoa Zoro",
      "color": "#59636f",
      "textColor": "#ffffff",
      "description": "Roronoa Zoro tag for One Piece Syrup Village retrieval and filtering.",
      "aliases": [],
      "parents": [],
      "sensitive": false,
      "deprecated": false,
      "replacement": ""
    },
    "character:sham": {
      "label": "Sham",
      "color": "#59636f",
      "textColor": "#ffffff",
      "description": "Sham tag for One Piece Syrup Village retrieval and filtering.",
      "aliases": [],
      "parents": [],
      "sensitive": false,
      "deprecated": false,
      "replacement": ""
    },
    "character:shanks": {
      "label": "Shanks",
      "color": "#59636f",
      "textColor": "#ffffff",
      "description": "Shanks tag for One Piece Syrup Village retrieval and filtering.",
      "aliases": [],
      "parents": [],
      "sensitive": false,
      "deprecated": false,
      "replacement": ""
    },
    "character:tamanegi": {
      "label": "Tamanegi",
      "color": "#59636f",
      "textColor": "#ffffff",
      "description": "Tamanegi tag for One Piece Syrup Village retrieval and filtering.",
      "aliases": [],
      "parents": [],
      "sensitive": false,
      "deprecated": false,
      "replacement": ""
    },
    "character:usopp": {
      "label": "Usopp",
      "color": "#59636f",
      "textColor": "#ffffff",
      "description": "Usopp tag for One Piece Syrup Village retrieval and filtering.",
      "aliases": [],
      "parents": [],
      "sensitive": false,
      "deprecated": false,
      "replacement": ""
    },
    "character:yasopp": {
      "label": "Yasopp",
      "color": "#59636f",
      "textColor": "#ffffff",
      "description": "Yasopp tag for One Piece Syrup Village retrieval and filtering.",
      "aliases": [],
      "parents": [],
      "sensitive": false,
      "deprecated": false,
      "replacement": ""
    },
    "continuity:one-piece-manga-main": {
      "label": "One Piece Manga Main",
      "color": "#59636f",
      "textColor": "#ffffff",
      "description": "One Piece Manga Main tag for One Piece Syrup Village retrieval and filtering.",
      "aliases": [],
      "parents": [],
      "sensitive": false,
      "deprecated": false,
      "replacement": ""
    },
    "faction:black-cat-pirates": {
      "label": "Black Cat Pirates",
      "color": "#59636f",
      "textColor": "#ffffff",
      "description": "Black Cat Pirates tag for One Piece Syrup Village retrieval and filtering.",
      "aliases": [],
      "parents": [],
      "sensitive": false,
      "deprecated": false,
      "replacement": ""
    },
    "faction:nyaban-brothers": {
      "label": "Nyaban Brothers",
      "color": "#59636f",
      "textColor": "#ffffff",
      "description": "Nyaban Brothers tag for One Piece Syrup Village retrieval and filtering.",
      "aliases": [],
      "parents": [],
      "sensitive": false,
      "deprecated": false,
      "replacement": ""
    },
    "faction:usopp-pirates": {
      "label": "Usopp Pirates",
      "color": "#59636f",
      "textColor": "#ffffff",
      "description": "Usopp Pirates tag for One Piece Syrup Village retrieval and filtering.",
      "aliases": [],
      "parents": [],
      "sensitive": false,
      "deprecated": false,
      "replacement": ""
    },
    "fandom:one-piece": {
      "label": "One Piece",
      "color": "#59636f",
      "textColor": "#ffffff",
      "description": "One Piece tag for One Piece Syrup Village retrieval and filtering.",
      "aliases": [],
      "parents": [],
      "sensitive": false,
      "deprecated": false,
      "replacement": ""
    },
    "item:going-merry": {
      "label": "Going Merry",
      "color": "#59636f",
      "textColor": "#ffffff",
      "description": "Going Merry tag for One Piece Syrup Village retrieval and filtering.",
      "aliases": [],
      "parents": [],
      "sensitive": false,
      "deprecated": false,
      "replacement": ""
    },
    "item:will": {
      "label": "Will",
      "color": "#59636f",
      "textColor": "#ffffff",
      "description": "Will tag for One Piece Syrup Village retrieval and filtering.",
      "aliases": [],
      "parents": [],
      "sensitive": false,
      "deprecated": false,
      "replacement": ""
    },
    "location:coastal-slope": {
      "label": "Coastal Slope",
      "color": "#59636f",
      "textColor": "#ffffff",
      "description": "Coastal Slope tag for One Piece Syrup Village retrieval and filtering.",
      "aliases": [],
      "parents": [],
      "sensitive": false,
      "deprecated": false,
      "replacement": ""
    },
    "location:kaya-mansion": {
      "label": "Kaya Mansion",
      "color": "#59636f",
      "textColor": "#ffffff",
      "description": "Kaya Mansion tag for One Piece Syrup Village retrieval and filtering.",
      "aliases": [],
      "parents": [],
      "sensitive": false,
      "deprecated": false,
      "replacement": ""
    },
    "location:syrup-village": {
      "label": "Syrup Village",
      "color": "#59636f",
      "textColor": "#ffffff",
      "description": "Syrup Village tag for One Piece Syrup Village retrieval and filtering.",
      "aliases": [],
      "parents": [],
      "sensitive": false,
      "deprecated": false,
      "replacement": ""
    },
    "quality:reviewed-baseline": {
      "label": "Reviewed Baseline",
      "color": "#59636f",
      "textColor": "#ffffff",
      "description": "Reviewed Baseline tag for One Piece Syrup Village retrieval and filtering.",
      "aliases": [],
      "parents": [],
      "sensitive": false,
      "deprecated": false,
      "replacement": ""
    },
    "rule:hypnosis": {
      "label": "Hypnosis",
      "color": "#59636f",
      "textColor": "#ffffff",
      "description": "Hypnosis tag for One Piece Syrup Village retrieval and filtering.",
      "aliases": [],
      "parents": [],
      "sensitive": false,
      "deprecated": false,
      "replacement": ""
    },
    "saga:east-blue": {
      "label": "East Blue",
      "color": "#59636f",
      "textColor": "#ffffff",
      "description": "East Blue tag for One Piece Syrup Village retrieval and filtering.",
      "aliases": [],
      "parents": [],
      "sensitive": false,
      "deprecated": false,
      "replacement": ""
    },
    "structure:arc-split-loredeck": {
      "label": "Arc Split Loredeck",
      "color": "#59636f",
      "textColor": "#ffffff",
      "description": "Arc Split Loredeck tag for One Piece Syrup Village retrieval and filtering.",
      "aliases": [],
      "parents": [],
      "sensitive": false,
      "deprecated": false,
      "replacement": ""
    },
    "topic:absent-father": {
      "label": "Absent Father",
      "color": "#59636f",
      "textColor": "#ffffff",
      "description": "Absent Father tag for One Piece Syrup Village retrieval and filtering.",
      "aliases": [],
      "parents": [],
      "sensitive": false,
      "deprecated": false,
      "replacement": ""
    },
    "topic:assassination-plot": {
      "label": "Assassination Plot",
      "color": "#59636f",
      "textColor": "#ffffff",
      "description": "Assassination Plot tag for One Piece Syrup Village retrieval and filtering.",
      "aliases": [],
      "parents": [],
      "sensitive": false,
      "deprecated": false,
      "replacement": ""
    },
    "topic:before-reveal-persona": {
      "label": "Before Reveal Persona",
      "color": "#59636f",
      "textColor": "#ffffff",
      "description": "Before Reveal Persona tag for One Piece Syrup Village retrieval and filtering.",
      "aliases": [],
      "parents": [],
      "sensitive": false,
      "deprecated": false,
      "replacement": ""
    },
    "topic:betrayed-trust": {
      "label": "Betrayed Trust",
      "color": "#59636f",
      "textColor": "#ffffff",
      "description": "Betrayed Trust tag for One Piece Syrup Village retrieval and filtering.",
      "aliases": [],
      "parents": [],
      "sensitive": false,
      "deprecated": false,
      "replacement": ""
    },
    "topic:crew-contempt": {
      "label": "Crew Contempt",
      "color": "#59636f",
      "textColor": "#ffffff",
      "description": "Crew Contempt tag for One Piece Syrup Village retrieval and filtering.",
      "aliases": [],
      "parents": [],
      "sensitive": false,
      "deprecated": false,
      "replacement": ""
    },
    "topic:daily-false-warnings": {
      "label": "Daily False Warnings",
      "color": "#59636f",
      "textColor": "#ffffff",
      "description": "Daily False Warnings tag for One Piece Syrup Village retrieval and filtering.",
      "aliases": [],
      "parents": [],
      "sensitive": false,
      "deprecated": false,
      "replacement": ""
    },
    "topic:defending-doubters": {
      "label": "Defending Doubters",
      "color": "#59636f",
      "textColor": "#ffffff",
      "description": "Defending Doubters tag for One Piece Syrup Village retrieval and filtering.",
      "aliases": [],
      "parents": [],
      "sensitive": false,
      "deprecated": false,
      "replacement": ""
    },
    "topic:domestic-betrayal": {
      "label": "Domestic Betrayal",
      "color": "#59636f",
      "textColor": "#ffffff",
      "description": "Domestic Betrayal tag for One Piece Syrup Village retrieval and filtering.",
      "aliases": [],
      "parents": [],
      "sensitive": false,
      "deprecated": false,
      "replacement": ""
    },
    "topic:first-real-ship": {
      "label": "First Real Ship",
      "color": "#59636f",
      "textColor": "#ffffff",
      "description": "First Real Ship tag for One Piece Syrup Village retrieval and filtering.",
      "aliases": [],
      "parents": [],
      "sensitive": false,
      "deprecated": false,
      "replacement": ""
    },
    "topic:forest-rescue": {
      "label": "Forest Rescue",
      "color": "#59636f",
      "textColor": "#ffffff",
      "description": "Forest Rescue tag for One Piece Syrup Village retrieval and filtering.",
      "aliases": [],
      "parents": [],
      "sensitive": false,
      "deprecated": false,
      "replacement": ""
    },
    "topic:gratitude-gift": {
      "label": "Gratitude Gift",
      "color": "#59636f",
      "textColor": "#ffffff",
      "description": "Gratitude Gift tag for One Piece Syrup Village retrieval and filtering.",
      "aliases": [],
      "parents": [],
      "sensitive": false,
      "deprecated": false,
      "replacement": ""
    },
    "topic:hypnosis-coercion": {
      "label": "Hypnosis Coercion",
      "color": "#59636f",
      "textColor": "#ffffff",
      "description": "Hypnosis Coercion tag for One Piece Syrup Village retrieval and filtering.",
      "aliases": [],
      "parents": [],
      "sensitive": false,
      "deprecated": false,
      "replacement": ""
    },
    "topic:hypnosis-threat": {
      "label": "Hypnosis Threat",
      "color": "#59636f",
      "textColor": "#ffffff",
      "description": "Hypnosis Threat tag for One Piece Syrup Village retrieval and filtering.",
      "aliases": [],
      "parents": [],
      "sensitive": false,
      "deprecated": false,
      "replacement": ""
    },
    "topic:kaya-isolation": {
      "label": "Kaya Isolation",
      "color": "#59636f",
      "textColor": "#ffffff",
      "description": "Kaya Isolation tag for One Piece Syrup Village retrieval and filtering.",
      "aliases": [],
      "parents": [],
      "sensitive": false,
      "deprecated": false,
      "replacement": ""
    },
    "topic:kaya-rescue": {
      "label": "Kaya Rescue",
      "color": "#59636f",
      "textColor": "#ffffff",
      "description": "Kaya Rescue tag for One Piece Syrup Village retrieval and filtering.",
      "aliases": [],
      "parents": [],
      "sensitive": false,
      "deprecated": false,
      "replacement": ""
    },
    "topic:klahadore-persona": {
      "label": "Klahadore Persona",
      "color": "#59636f",
      "textColor": "#ffffff",
      "description": "Klahadore Persona tag for One Piece Syrup Village retrieval and filtering.",
      "aliases": [],
      "parents": [],
      "sensitive": false,
      "deprecated": false,
      "replacement": ""
    },
    "topic:kuro-defeat": {
      "label": "Kuro Defeat",
      "color": "#59636f",
      "textColor": "#ffffff",
      "description": "Kuro Defeat tag for One Piece Syrup Village retrieval and filtering.",
      "aliases": [],
      "parents": [],
      "sensitive": false,
      "deprecated": false,
      "replacement": ""
    },
    "topic:landing-timing": {
      "label": "Landing Timing",
      "color": "#59636f",
      "textColor": "#ffffff",
      "description": "Landing Timing tag for One Piece Syrup Village retrieval and filtering.",
      "aliases": [],
      "parents": [],
      "sensitive": false,
      "deprecated": false,
      "replacement": ""
    },
    "topic:luffy-recruitment-sense": {
      "label": "Luffy Recruitment Sense",
      "color": "#59636f",
      "textColor": "#ffffff",
      "description": "Luffy Recruitment Sense tag for One Piece Syrup Village retrieval and filtering.",
      "aliases": [],
      "parents": [],
      "sensitive": false,
      "deprecated": false,
      "replacement": ""
    },
    "topic:mansion-isolation": {
      "label": "Mansion Isolation",
      "color": "#59636f",
      "textColor": "#ffffff",
      "description": "Mansion Isolation tag for One Piece Syrup Village retrieval and filtering.",
      "aliases": [],
      "parents": [],
      "sensitive": false,
      "deprecated": false,
      "replacement": ""
    },
    "topic:merry-steward": {
      "label": "Merry Steward",
      "color": "#59636f",
      "textColor": "#ffffff",
      "description": "Merry Steward tag for One Piece Syrup Village retrieval and filtering.",
      "aliases": [],
      "parents": [],
      "sensitive": false,
      "deprecated": false,
      "replacement": ""
    },
    "topic:nyaban-brothers": {
      "label": "Nyaban Brothers",
      "color": "#59636f",
      "textColor": "#ffffff",
      "description": "Nyaban Brothers tag for One Piece Syrup Village retrieval and filtering.",
      "aliases": [],
      "parents": [],
      "sensitive": false,
      "deprecated": false,
      "replacement": ""
    },
    "topic:offshore-crew": {
      "label": "Offshore Crew",
      "color": "#59636f",
      "textColor": "#ffffff",
      "description": "Offshore Crew tag for One Piece Syrup Village retrieval and filtering.",
      "aliases": [],
      "parents": [],
      "sensitive": false,
      "deprecated": false,
      "replacement": ""
    },
    "topic:play-pirate-crew": {
      "label": "Play Pirate Crew",
      "color": "#59636f",
      "textColor": "#ffffff",
      "description": "Play Pirate Crew tag for One Piece Syrup Village retrieval and filtering.",
      "aliases": [],
      "parents": [],
      "sensitive": false,
      "deprecated": false,
      "replacement": ""
    },
    "topic:quiet-departure": {
      "label": "Quiet Departure",
      "color": "#59636f",
      "textColor": "#ffffff",
      "description": "Quiet Departure tag for One Piece Syrup Village retrieval and filtering.",
      "aliases": [],
      "parents": [],
      "sensitive": false,
      "deprecated": false,
      "replacement": ""
    },
    "topic:quiet-village-stakes": {
      "label": "Quiet Village Stakes",
      "color": "#59636f",
      "textColor": "#ffffff",
      "description": "Quiet Village Stakes tag for One Piece Syrup Village retrieval and filtering.",
      "aliases": [],
      "parents": [],
      "sensitive": false,
      "deprecated": false,
      "replacement": ""
    },
    "topic:ship-design": {
      "label": "Ship Design",
      "color": "#59636f",
      "textColor": "#ffffff",
      "description": "Ship Design tag for One Piece Syrup Village retrieval and filtering.",
      "aliases": [],
      "parents": [],
      "sensitive": false,
      "deprecated": false,
      "replacement": ""
    },
    "topic:ship-motive": {
      "label": "Ship Motive",
      "color": "#59636f",
      "textColor": "#ffffff",
      "description": "Ship Motive tag for One Piece Syrup Village retrieval and filtering.",
      "aliases": [],
      "parents": [],
      "sensitive": false,
      "deprecated": false,
      "replacement": ""
    },
    "topic:slope-defense-timing": {
      "label": "Slope Defense Timing",
      "color": "#59636f",
      "textColor": "#ffffff",
      "description": "Slope Defense Timing tag for One Piece Syrup Village retrieval and filtering.",
      "aliases": [],
      "parents": [],
      "sensitive": false,
      "deprecated": false,
      "replacement": ""
    },
    "topic:small-boat-transition": {
      "label": "Small Boat Transition",
      "color": "#59636f",
      "textColor": "#ffffff",
      "description": "Small Boat Transition tag for One Piece Syrup Village retrieval and filtering.",
      "aliases": [],
      "parents": [],
      "sensitive": false,
      "deprecated": false,
      "replacement": ""
    },
    "topic:small-group-defense": {
      "label": "Small Group Defense",
      "color": "#59636f",
      "textColor": "#ffffff",
      "description": "Small Group Defense tag for One Piece Syrup Village retrieval and filtering.",
      "aliases": [],
      "parents": [],
      "sensitive": false,
      "deprecated": false,
      "replacement": ""
    },
    "topic:sniper-improvisation": {
      "label": "Sniper Improvisation",
      "color": "#59636f",
      "textColor": "#ffffff",
      "description": "Sniper Improvisation tag for One Piece Syrup Village retrieval and filtering.",
      "aliases": [],
      "parents": [],
      "sensitive": false,
      "deprecated": false,
      "replacement": ""
    },
    "topic:terrified-defender": {
      "label": "Terrified Defender",
      "color": "#59636f",
      "textColor": "#ffffff",
      "description": "Terrified Defender tag for One Piece Syrup Village retrieval and filtering.",
      "aliases": [],
      "parents": [],
      "sensitive": false,
      "deprecated": false,
      "replacement": ""
    },
    "topic:truth-no-one-believes": {
      "label": "Truth No One Believes",
      "color": "#59636f",
      "textColor": "#ffffff",
      "description": "Truth No One Believes tag for One Piece Syrup Village retrieval and filtering.",
      "aliases": [],
      "parents": [],
      "sensitive": false,
      "deprecated": false,
      "replacement": ""
    },
    "topic:usopp-joins": {
      "label": "Usopp Joins",
      "color": "#59636f",
      "textColor": "#ffffff",
      "description": "Usopp Joins tag for One Piece Syrup Village retrieval and filtering.",
      "aliases": [],
      "parents": [],
      "sensitive": false,
      "deprecated": false,
      "replacement": ""
    }
  }
}
